{
  "driver_1": {
    "name": "Max Vershaeren",
    "offers": [
      {
        "name": "Hiro Tanaka",
        "team": "Racing 404",
        "points": 0,
        "rating": 5.1159
      },
      {
        "name": "Diego Ventura",
        "team": "Formula 1.0 racing team",
        "points": 0,
        "rating": 5.3375
      },
      {
        "name": "Sebastian Krell",
        "team": "JavaScript Racing team",
        "points": 0,
        "rating": 5.0881
      },
      {
        "name": "Leo Krüger",
        "team": "PyCharm motors",
        "points": 0,
        "rating": 5.5073
      },
      {
        "name": "Theo Hartman",
        "team": "Underbyte Nvidia GP",
        "points": 0,
        "rating": 5.0076
      },
      {
        "name": "Enzo DaCosta",
        "team": "JavaScript Racing team",
        "points": 0,
        "rating": 5.0126
      },
      {
        "name": "Tyler Quinn",
        "team": "Jawa Surenate Linux racing team",
        "points": 0,
        "rating": 5.3723
      },
      {
        "name": "Elias Northgate",
        "team": "AMD Assemblyte GP",
        "points": 0,
        "rating": 5.4126
      }
    ]
  },
  "driver_2": {
    "name": "Kim Nguyen",
    "offers": [
      {
        "name": "Alex Storme",
        "team": "Scuderia Python",
        "points": 0,
        "rating": 5.3688
      },
      {
        "name": "Enzo DaCosta",
        "team": "JavaScript Racing team",
        "points": 0,
        "rating": 5.0126
      },
      {
        "name": "Felipe Marquez",
        "team": "AMD Assemblyte GP",
        "points": 0,
        "rating": 5.6202
      },
      {
        "name": "Hiro Tanaka",
        "team": "Racing 404",
        "points": 0,
        "rating": 5.1159
      },
      {
        "name": "Theo Hartman",
        "team": "Underbyte Nvidia GP",
        "points": 0,
        "rating": 5.0076
      },
      {
        "name": "Sebastian Krell",
        "team": "JavaScript Racing team",
        "points": 0,
        "rating": 5.0881
      },
      {
        "name": "Tyler Quinn",
        "team": "Jawa Surenate Linux racing team",
        "points": 0,
        "rating": 5.3723
      },
      {
        "name": "Elias Northgate",
        "team": "AMD Assemblyte GP",
        "points": 0,
        "rating": 5.4126
      }
    ]
  },
  "mmr2_best": {
    "name": "Rafael Ortega",
    "rating": 0.9046
  }
}